hybrid/__init__.py
hybrid/background_tasks.py
hybrid/client.py
hybrid/element.py
hybrid/embedded_encoder.py
hybrid/events.py
hybrid/globals.py
hybrid/hybrid.py
hybrid/interface.py
hybrid/page.py
hybrid/style.py
hybrid/system_spezifisch.py
hybrid/utils.py
hybrid/charts/all_charts.py
hybrid/charts/m.py
hybrid/core/chrome_engine.py
hybrid/core/context.py
hybrid/core/electron.py
hybrid/core/event_core.py
hybrid/core/event_core_.py
hybrid/elements/affix.py
hybrid/elements/alert.py
hybrid/elements/anchour.py
hybrid/elements/autocomplete.py
hybrid/elements/avatar.py
hybrid/elements/badge.py
hybrid/elements/breadcrumb.py
hybrid/elements/button.py
hybrid/elements/calendar.py
hybrid/elements/card.py
hybrid/elements/carousel.py
hybrid/elements/cascder.py
hybrid/elements/checkbox.py
hybrid/elements/collapse.py
hybrid/elements/colorpicker.py
hybrid/elements/column.py
hybrid/elements/content.py
hybrid/elements/datepicker.py
hybrid/elements/desccriptions.py
hybrid/elements/divider.py
hybrid/elements/drawer.py
hybrid/elements/dropdown.py
hybrid/elements/empty.py
hybrid/elements/floatbutton.py
hybrid/elements/footer.py
hybrid/elements/form.py
hybrid/elements/header.py
hybrid/elements/icons.py
hybrid/elements/image.py
hybrid/elements/input.py
hybrid/elements/layout.py
hybrid/elements/list.py
hybrid/elements/mentions.py
hybrid/elements/menu.py
hybrid/elements/message.py
hybrid/elements/modal.py
hybrid/elements/navigation.py
hybrid/elements/notifications.py
hybrid/elements/pagination.py
hybrid/elements/player.py
hybrid/elements/popconfirm.py
hybrid/elements/popover.py
hybrid/elements/progress.py
hybrid/elements/qrcode.py
hybrid/elements/radio.py
hybrid/elements/rate.py
hybrid/elements/result.py
hybrid/elements/row.py
hybrid/elements/segmented.py
hybrid/elements/select.py
hybrid/elements/sider.py
hybrid/elements/skeleton.py
hybrid/elements/slider.py
hybrid/elements/space.py
hybrid/elements/spin.py
hybrid/elements/statistic.py
hybrid/elements/steps.py
hybrid/elements/switch.py
HybridUI-0.0.9.dist-info/LICENSE
HybridUI-0.0.9.dist-info/METADATA
HybridUI-0.0.9.dist-info/WHEEL
HybridUI-0.0.9.dist-info/top_level.txt
HybridUI-0.0.9.dist-info/RECORD
