Metadata-Version: 2.1
Name: HybridUI
Version: 0.0.9
Summary: Create an efficient and enjoyable work experience with pure Python
Home-page: https://github.com/AriBermeki/hybridui
Author: Ari Bermeki
Author-email: ari.bermeki.de@gmail.com
Classifier: Development Status :: 3 - Alpha
Classifier: Environment :: Web Environment
Classifier: Intended Audience :: Developers
Classifier: Programming Language :: Python :: 3.9
Classifier: License :: OSI Approved :: MIT License
Classifier: Operating System :: OS Independent
Classifier: Topic :: Internet :: WWW/HTTP
Requires-Python: >=3.9
License-File: LICENSE
Requires-Dist: fastapi
Requires-Dist: fastapi-socketio
Requires-Dist: python-socketio
Requires-Dist: uvicorn[standard]
Requires-Dist: psutil
Requires-Dist: python-dateutil
Requires-Dist: python-multipart
Requires-Dist: jinja2
Requires-Dist: aiofiles
Requires-Dist: starlette
Provides-Extra: full
Requires-Dist: graphene ; extra == 'full'
Requires-Dist: itsdangerous ; extra == 'full'
Requires-Dist: pyyaml ; extra == 'full'
Requires-Dist: requests ; extra == 'full'
Requires-Dist: orjson ; extra == 'full'
